openccpy/__init__.py
openccpy/opencc.py
openccpy/opencc_const.py
openccpy/opencc_dict.py
openccpy/opencc_util.py
openccpy/db/STCharacters.txt
openccpy/db/STPhrases.txt
openccpy/db/TSCharacters.txt
openccpy/db/TSPhrases.txt
test/__init__.py
test/test_opencc.py
test/test_opencc_const.py
test/test_opencc_dict.py
test/test_opencc_util.py
openccpy-0.0.4.3.dist-info/LICENSE
openccpy-0.0.4.3.dist-info/METADATA
openccpy-0.0.4.3.dist-info/WHEEL
openccpy-0.0.4.3.dist-info/top_level.txt
openccpy-0.0.4.3.dist-info/RECORD
