Metadata-Version: 2.1
Name: openccpy
Version: 0.0.4.3
Summary: Open Chinese Convert is an opensource project for conversion between Traditional Chinese and Simplified Chinese for python.
Home-page: https://github.com/houbb/pycc
Author: houbb
Author-email: houbinbin.echo@gmail.com
License: UNKNOWN
Keywords: tool,opencc,opencc-py,opencc-python,Chinese Convert,中文繁简体转换
Platform: UNKNOWN
Classifier: Programming Language :: Python :: 3
Classifier: License :: OSI Approved :: MIT License
Classifier: Operating System :: OS Independent
